hidef/__init__.py
hidef/dash_utils.py
hidef/hidef_finder.py
hidef/logger.py
hidef/utils.py
hidef/weaver.py
hidef-1.1.5.data/scripts/hidef_finder.py
hidef-1.1.5.dist-info/LICENSE
hidef-1.1.5.dist-info/METADATA
hidef-1.1.5.dist-info/WHEEL
hidef-1.1.5.dist-info/top_level.txt
hidef-1.1.5.dist-info/RECORD
