Metadata-Version: 2.1
Name: hidef
Version: 1.1.5
Summary: A package for building a hierarchy based on multiple partitions on graph nodes.
Home-page: https://github.com/fanzheng10/HiDeF
Author: Fan Zheng, She Zhang
Author-email: fanzheng1101@gmail.com
License: UNKNOWN
Project-URL: Bug Reports, https://github.com/fanzheng10/HiDeF/issues
Project-URL: Source, https://github.com/fanzheng10/HiDeF
Keywords: hierarchy tree DAG
Platform: UNKNOWN
Classifier: Development Status :: 3 - Alpha
Classifier: Intended Audience :: Science/Research
Classifier: Topic :: Scientific/Engineering :: Bio-Informatics
Classifier: License :: OSI Approved :: MIT License
Classifier: Programming Language :: Python :: 3.6
Classifier: Programming Language :: Python :: 3.7
Classifier: Programming Language :: Python :: 3.8
Requires-Python: >=3.6, <4
Requires-Dist: numpy (>=1.19.2)
Requires-Dist: networkx (>=2.3)
Requires-Dist: scipy (>=1.3.1)
Requires-Dist: pandas (>=0.25.1)
Requires-Dist: louvain (>=0.6.1)
Requires-Dist: leidenalg (>=0.7.0)
Requires-Dist: scikit-learn (>=0.23.1)
